late/__init__.py
late/_version.py
test/__init__.py
test/complex_test.py
test/dataclass_test.py
test/generator_test.py
test/iterator_test.py
test/simple_test.py
Late-1.2.2.dist-info/LICENSE
Late-1.2.2.dist-info/METADATA
Late-1.2.2.dist-info/WHEEL
Late-1.2.2.dist-info/top_level.txt
Late-1.2.2.dist-info/RECORD
